qstat/__init__.py
qstat/_tools.py
qstat/tests/resources/qstat_empty_queue.xml
qstat/tests/resources/qstat_example.stdout
qstat/tests/resources/qstat_example.xml
qstat/tests/resources/qstat_length_one.xml
qstat-0.0.5.dist-info/LICENSE
qstat-0.0.5.dist-info/METADATA
qstat-0.0.5.dist-info/WHEEL
qstat-0.0.5.dist-info/top_level.txt
qstat-0.0.5.dist-info/RECORD
